spicemodels/__init__.py
spicemodels/main.py
spicemodels-2.6.dist-info/METADATA
spicemodels-2.6.dist-info/WHEEL
spicemodels-2.6.dist-info/top_level.txt
spicemodels-2.6.dist-info/RECORD
